{
  "lineage": {
    "entities": [
      {
        "access": [
          {
            "accessMethod": "Read checked-out CME submodule path",
            "alternateUrls": [],
            "contact": null,
            "cost": "not_applicable",
            "entityId": "artifact:general-corpus:ChaucerAstr",
            "entityLabel": "General Corpus source XML for ChaucerAstr",
            "entityType": "repository_artifact",
            "format": "XML",
            "id": "access:astr-repo",
            "lastChecked": "2026-07-11",
            "localCopies": [],
            "notes": [],
            "provider": "Kyvero Press",
            "resourceKind": "repository_file",
            "rights": [],
            "status": "local_only",
            "url": null
          }
        ],
        "bibliographic": null,
        "dateStatements": [],
        "description": "Repository XML supplied through the CME submodule.",
        "holding": null,
        "id": "artifact:general-corpus:ChaucerAstr",
        "identifiers": [
          {
            "scheme": "CME/UMDL",
            "value": "ChaucerAstr"
          },
          {
            "scheme": "git-blob",
            "value": "f2a1b7bb34cd19b615ec764669838c8fdb108f9e"
          }
        ],
        "label": "General Corpus source XML for ChaucerAstr",
        "notes": [],
        "physicalDescription": null,
        "rights": [
          {
            "as_of": "2026-07-11",
            "basis": "The underlying text and edition are public domain in the United States, but the XML embeds an express redistribution restriction.",
            "component": "The local U-M-derived XML encoding",
            "confidence": "high",
            "contract_terms_status": "provider_terms_apply",
            "copyright_status": "public_domain",
            "entity": "artifact:general-corpus:ChaucerAstr",
            "evidence_ids": [
              "evidence:astr-xml",
              "evidence:umich-astr"
            ],
            "id": "rights:astr-local-terms",
            "jurisdiction": "Provider terms"
          }
        ],
        "survivalStatus": "not_applicable",
        "type": "repository_artifact"
      },
      {
        "access": [
          {
            "accessMethod": "U-M item and full text",
            "alternateUrls": [],
            "contact": null,
            "cost": "free",
            "entityId": "encoding:umich-cme:ChaucerAstr",
            "entityLabel": "University of Michigan CME item ChaucerAstr",
            "entityType": "digital_encoding",
            "format": "HTML digital text",
            "id": "access:astr-umich",
            "lastChecked": "2026-07-11",
            "localCopies": [],
            "notes": [],
            "provider": "University of Michigan Library",
            "resourceKind": "digital_text",
            "rights": [],
            "status": "publicly_available",
            "url": "https://name.umdl.umich.edu/ChaucerAstr"
          }
        ],
        "bibliographic": null,
        "dateStatements": [
          {
            "certainty": "high",
            "evidence_ids": [
              "evidence:astr-xml",
              "evidence:umich-astr"
            ],
            "label": "electronic publication",
            "normalized": "1997",
            "value": "1997"
          }
        ],
        "description": "Public electronic text created by OCR and correction from Skeat's EETS edition in 1997.",
        "holding": null,
        "id": "encoding:umich-cme:ChaucerAstr",
        "identifiers": [
          {
            "scheme": "UMDL handle",
            "uri": "https://name.umdl.umich.edu/ChaucerAstr",
            "value": "ChaucerAstr"
          }
        ],
        "label": "University of Michigan CME item ChaucerAstr",
        "notes": [],
        "physicalDescription": null,
        "rights": [
          {
            "as_of": "2026-07-11",
            "asserted_by_id": "agent:umich",
            "basis": "U-M labels the item public domain and No Copyright–United States.",
            "component": "Materials presented in U-M CME item ChaucerAstr",
            "confidence": "high",
            "contract_terms_status": "provider_terms_apply",
            "copyright_status": "public_domain",
            "entity": "encoding:umich-cme:ChaucerAstr",
            "evidence_ids": [
              "evidence:umich-astr",
              "evidence:astr-xml"
            ],
            "id": "rights:umich-astr-us",
            "jurisdiction": "United States",
            "notes": [
              "The XML's 1997 availability notice prohibits redistribution by commercial and not-for-profit content providers; whether the current statement supersedes it is unresolved."
            ],
            "rights_statement_uri": "https://rightsstatements.org/page/NoC-US/1.0/"
          }
        ],
        "survivalStatus": "extant",
        "type": "digital_encoding"
      },
      {
        "access": [
          {
            "accessMethod": "Public scan with exact direct PDF download",
            "alternateUrls": [
              "https://archive.org/details/onastrol00chautreatiserich",
              "https://archive.org/download/onastrol00chautreatiserich/onastrol00chautreatiserich.pdf"
            ],
            "contact": null,
            "cost": "free",
            "entityId": "edition:skeat:astrolabe-1872",
            "entityLabel": "Skeat 1872 edition of A Treatise on the Astrolabe",
            "entityType": "scholarly_edition",
            "format": "Google Books/Internet Archive complete page-image PDF",
            "id": "access:skeat-scan",
            "lastChecked": "2026-07-11",
            "localCopies": [
              {
                "available": false,
                "bundleSourceKind": null,
                "bytes": 15710387,
                "coverage": "complete",
                "downloadedOn": "2026-07-11",
                "label": "Skeat Astrolabe 1872 complete scan",
                "mediaType": "application/pdf",
                "notes": [
                  "Complete 220-page provider PDF, retaining scan matter, preface, edited Middle English text, critical and additional notes, Latin comparison text, glossary, publication lists, and library matter."
                ],
                "path": "source-cache/ChaucerAstr/skeat-astrolabe-1872-complete.pdf",
                "retrievalMethod": "direct_download",
                "sha256": "4d728c89b68fb7d2f253e6ccd43fedf02c0803b33afb0ea0ed01caa31daea2bf",
                "sizeLabel": "15.0 MiB",
                "sourceFileCount": null,
                "sourceUrl": "https://archive.org/download/onastrol00chautreatiserich/onastrol00chautreatiserich.pdf",
                "workPortion": {
                  "endUrl": "https://archive.org/download/onastrol00chautreatiserich/onastrol00chautreatiserich.pdf#page=148",
                  "label": "Skeat's edited Middle English Treatise on the Astrolabe",
                  "locators": [
                    "printed pp. 1-60",
                    "PDF pages 89-148",
                    "Prologue; Part I; Part II.1-46 with supplied sections"
                  ],
                  "notes": [
                    "Direct page inspection places the opening Prologue at PDF page 89 and the end of the edited Middle English text at PDF page 148; critical notes begin on PDF page 149."
                  ],
                  "startUrl": "https://archive.org/download/onastrol00chautreatiserich/onastrol00chautreatiserich.pdf#page=89"
                }
              }
            ],
            "notes": [
              "The ignored local cache is a complete scan of the printed edition, not a manuscript facsimile and not a separate grant of scan-image reuse rights."
            ],
            "provider": null,
            "resourceKind": "page_images",
            "rights": [],
            "status": "publicly_available",
            "url": "https://books.google.com/books?id=rIINAAAAQAAJ"
          }
        ],
        "bibliographic": {
          "citation": "A Treatise on the Astrolabe; Addressed to His Son Lowys by Geoffrey Chaucer, A.D. 1391, ed. Walter W. Skeat, Early English Text Society, Extra Series 16 (London: N. Trübner & Co., 1872).",
          "date": "1872",
          "languages": [
            "enm",
            "lat",
            "eng"
          ],
          "publication_place": "London",
          "publisher": "N. Trübner & Co. for the Early English Text Society",
          "series": "Early English Text Society, Extra Series 16",
          "title": "A Treatise on the Astrolabe; Addressed to His Son Lowys by Geoffrey Chaucer, A.D. 1391"
        },
        "dateStatements": [
          {
            "certainty": "high",
            "evidence_ids": [
              "evidence:skeat-scan",
              "evidence:astr-xml"
            ],
            "label": "first publication",
            "normalized": "1872",
            "value": "1872"
          }
        ],
        "description": null,
        "holding": null,
        "id": "edition:skeat:astrolabe-1872",
        "identifiers": [],
        "label": "Skeat 1872 edition of A Treatise on the Astrolabe",
        "notes": [],
        "physicalDescription": null,
        "rights": [
          {
            "as_of": "2026-07-11",
            "basis": "The underlying texts were composed and copied centuries before modern copyright.",
            "component": "Medieval text attributed to Chaucer and anonymous supplementary conclusions",
            "confidence": "high",
            "contract_terms_status": "none_known",
            "copyright_status": "public_domain",
            "entity": "edition:skeat:astrolabe-1872",
            "evidence_ids": [
              "evidence:skeat-scan",
              "evidence:copyright-office"
            ],
            "id": "rights:astrolabe-text-us",
            "jurisdiction": "United States"
          },
          {
            "as_of": "2026-07-11",
            "basis": "First published in 1872; Skeat died in 1912.",
            "component": "Skeat's 1872 edition and editorial matter",
            "confidence": "high",
            "contract_terms_status": "none_known",
            "copyright_status": "public_domain",
            "entity": "edition:skeat:astrolabe-1872",
            "evidence_ids": [
              "evidence:skeat-scan",
              "evidence:copyright-office"
            ],
            "id": "rights:skeat-edition-us",
            "jurisdiction": "United States"
          }
        ],
        "survivalStatus": "extant",
        "type": "scholarly_edition"
      },
      {
        "access": [
          {
            "accessMethod": "Contact Cambridge University Library Manuscripts Department using shelfmark Dd.3.53",
            "alternateUrls": [],
            "contact": null,
            "cost": "unknown",
            "entityId": "witness:cul:Dd3-53",
            "entityLabel": "Cambridge University Library MS Dd.3.53",
            "entityType": "manuscript_witness",
            "format": null,
            "id": "access:dd353-enquiry",
            "lastChecked": "2026-07-11",
            "localCopies": [],
            "notes": [
              "No complete public facsimile was verified in this research pass."
            ],
            "provider": "Cambridge University Library",
            "resourceKind": "repository_enquiry",
            "rights": [],
            "status": "requestable",
            "url": "https://www.lib.cam.ac.uk/collections/departments/manuscripts-university-archives"
          }
        ],
        "bibliographic": null,
        "dateStatements": [],
        "description": "Skeat's base witness for the Prologue, Part I.1–23, and Part II.1–40; Skeat describes it as a vellum manuscript with diagrams.",
        "holding": {
          "catalog_url": "https://www.lib.cam.ac.uk/collections/departments/manuscripts-university-archives",
          "historical_designations": [],
          "institution_id": "agent:cul",
          "notes": "Exact online catalog or digitization record was not verified.",
          "shelfmark": "Dd.3.53"
        },
        "id": "witness:cul:Dd3-53",
        "identifiers": [
          {
            "scheme": "CUL shelfmark",
            "value": "Dd.3.53"
          }
        ],
        "label": "Cambridge University Library MS Dd.3.53",
        "notes": [],
        "physicalDescription": {
          "notes": [
            "Skeat's introduction reports diagrams in the witness."
          ],
          "support": "Vellum"
        },
        "rights": [
          {
            "as_of": "2026-07-11",
            "basis": "No image-specific license or complete reusable image set was verified.",
            "component": "Any modern photographs, scans, or supplied reproductions",
            "confidence": "high",
            "contract_terms_status": "provider_terms_apply",
            "copyright_status": "unknown",
            "entity": "witness:cul:Dd3-53",
            "evidence_ids": [
              "evidence:cul-manuscripts"
            ],
            "id": "rights:dd353-images",
            "jurisdiction": "Provider terms and intended place of reuse"
          }
        ],
        "survivalStatus": "extant",
        "type": "manuscript_witness"
      },
      {
        "access": [
          {
            "accessMethod": "Email St John's Special Collections and request an appointment using shelfmark E.2",
            "alternateUrls": [
              "https://www.joh.cam.ac.uk/research/library/old-library"
            ],
            "contact": null,
            "cost": "unknown",
            "entityId": "witness:stjohn:E2",
            "entityLabel": "St John's College Cambridge MS E.2",
            "entityType": "manuscript_witness",
            "format": null,
            "id": "access:e2-enquiry",
            "lastChecked": "2026-07-11",
            "localCopies": [],
            "notes": [
              "No complete public facsimile or item-specific image terms were verified in this research pass."
            ],
            "provider": "St John's College, Cambridge",
            "resourceKind": "repository_enquiry",
            "rights": [],
            "status": "requestable",
            "url": "https://www.joh.cam.ac.uk/contact-us"
          }
        ],
        "bibliographic": null,
        "dateStatements": [],
        "description": "Source in Skeat's edition for conclusions II.41–43 and II.46–50.",
        "holding": {
          "historical_designations": [],
          "institution_id": "agent:stjohn",
          "notes": "Exact online catalog or digitization record was not verified.",
          "shelfmark": "E.2"
        },
        "id": "witness:stjohn:E2",
        "identifiers": [
          {
            "scheme": "St John's College Cambridge shelfmark",
            "value": "E.2"
          }
        ],
        "label": "St John's College Cambridge MS E.2",
        "notes": [],
        "physicalDescription": null,
        "rights": [
          {
            "as_of": "2026-07-11",
            "basis": "The current Special Collections access pages do not provide item-specific image reuse terms for E.2.",
            "component": "Any modern photographs, scans, or supplied reproductions",
            "confidence": "medium",
            "contract_terms_status": "unknown",
            "copyright_status": "unknown",
            "entity": "witness:stjohn:E2",
            "evidence_ids": [
              "evidence:stjohn-special-collections"
            ],
            "id": "rights:e2-images",
            "jurisdiction": "Provider terms and intended place of reuse"
          }
        ],
        "survivalStatus": "extant",
        "type": "manuscript_witness"
      },
      {
        "access": [
          {
            "accessMethod": "Request or enquire through Bodleian Special Collections using shelfmark MS. Digby 72",
            "alternateUrls": [
              "https://www.bodleian.ox.ac.uk/collections-and-resources/special-collections/ordering/requests",
              "https://archives.bodleian.ox.ac.uk/repositories/2/resources/7554"
            ],
            "contact": null,
            "cost": "unknown",
            "entityId": "witness:bodleian:Digby72",
            "entityLabel": "Bodleian Library MS Digby 72",
            "entityType": "manuscript_witness",
            "format": null,
            "id": "access:digby72-enquiry",
            "lastChecked": "2026-07-11",
            "localCopies": [],
            "notes": [
              "No complete public facsimile was verified in this research pass."
            ],
            "provider": "Bodleian Libraries, University of Oxford",
            "resourceKind": "repository_enquiry",
            "rights": [],
            "status": "requestable",
            "url": "https://www.bodleian.ox.ac.uk/collections-and-resources/special-collections/using"
          }
        ],
        "bibliographic": null,
        "dateStatements": [],
        "description": "Source in Skeat's edition for conclusions II.44–45.",
        "holding": {
          "historical_designations": [],
          "institution_id": "agent:bodleian",
          "notes": "The online Digby collection record confirms the shelfmark range, but an item-level catalogue or image record was not verified.",
          "shelfmark": "MS. Digby 72"
        },
        "id": "witness:bodleian:Digby72",
        "identifiers": [
          {
            "scheme": "Bodleian shelfmark",
            "value": "MS. Digby 72"
          }
        ],
        "label": "Bodleian Library MS Digby 72",
        "notes": [],
        "physicalDescription": null,
        "rights": [
          {
            "as_of": "2026-07-11",
            "basis": "Bodleian-supplied and Digital Bodleian images carry provider terms; no item-specific Digby 72 image license was verified.",
            "component": "Any modern photographs, scans, or supplied reproductions",
            "confidence": "high",
            "contract_terms_status": "provider_terms_apply",
            "copyright_status": "unknown",
            "entity": "witness:bodleian:Digby72",
            "evidence_ids": [
              "evidence:bodleian-image-terms"
            ],
            "id": "rights:digby72-images",
            "jurisdiction": "Provider terms and intended place of reuse"
          }
        ],
        "survivalStatus": "extant",
        "type": "manuscript_witness"
      },
      {
        "access": [
          {
            "accessMethod": "Request or enquire through Bodleian Special Collections using shelfmark MS. Bodley 619",
            "alternateUrls": [
              "https://www.bodleian.ox.ac.uk/collections-and-resources/special-collections/ordering/requests"
            ],
            "contact": null,
            "cost": "unknown",
            "entityId": "witness:bodleian:Bodley619",
            "entityLabel": "Bodleian Library MS Bodley 619",
            "entityType": "manuscript_witness",
            "format": null,
            "id": "access:bodley619-enquiry",
            "lastChecked": "2026-07-11",
            "localCopies": [],
            "notes": [
              "No complete public facsimile was verified in this research pass."
            ],
            "provider": "Bodleian Libraries, University of Oxford",
            "resourceKind": "repository_enquiry",
            "rights": [],
            "status": "requestable",
            "url": "https://www.bodleian.ox.ac.uk/collections-and-resources/special-collections/using"
          }
        ],
        "bibliographic": null,
        "dateStatements": [],
        "description": "Source in Skeat's edition for conclusion II.51.",
        "holding": {
          "historical_designations": [],
          "institution_id": "agent:bodleian",
          "notes": "An item-level public catalogue or image record was not verified.",
          "shelfmark": "MS. Bodley 619"
        },
        "id": "witness:bodleian:Bodley619",
        "identifiers": [
          {
            "scheme": "Bodleian shelfmark",
            "value": "MS. Bodley 619"
          }
        ],
        "label": "Bodleian Library MS Bodley 619",
        "notes": [],
        "physicalDescription": null,
        "rights": [
          {
            "as_of": "2026-07-11",
            "basis": "Bodleian-supplied and Digital Bodleian images carry provider terms; no item-specific Bodley 619 image license was verified.",
            "component": "Any modern photographs, scans, or supplied reproductions",
            "confidence": "high",
            "contract_terms_status": "provider_terms_apply",
            "copyright_status": "unknown",
            "entity": "witness:bodleian:Bodley619",
            "evidence_ids": [
              "evidence:bodleian-image-terms"
            ],
            "id": "rights:bodley619-images",
            "jurisdiction": "Provider terms and intended place of reuse"
          }
        ],
        "survivalStatus": "extant",
        "type": "manuscript_witness"
      }
    ],
    "lastReviewed": "2026-07-11",
    "manifestId": "lineage:ChaucerAstr",
    "openQuestions": [
      {
        "evidence_ids": [
          "evidence:astr-xml",
          "evidence:supplement-authorship"
        ],
        "id": "question:astr-supplement-authorship",
        "impact": "high",
        "last_checked": "2026-07-11",
        "next_steps": [
          "Consult the Variorum textual introduction and current manuscript scholarship; preserve the core/supplement distinction in display and attribution."
        ],
        "question": "Which, if any, conclusions after Part II.40 are Chaucer's rather than later supplements?",
        "status": "unresolved"
      },
      {
        "evidence_ids": [
          "evidence:astr-xml",
          "evidence:skeat-scan"
        ],
        "id": "question:astr-emendations",
        "impact": "medium",
        "last_checked": "2026-07-11",
        "next_steps": [
          "Collate the XML against the 1872 page images and then against the four manuscripts or licensed reproductions."
        ],
        "question": "Which individual readings, brackets, diagrams, and omissions in the XML reflect Skeat's intervention, manuscript evidence, or OCR correction?",
        "status": "unresolved"
      },
      {
        "evidence_ids": [
          "evidence:cul-manuscripts",
          "evidence:stjohn-special-collections",
          "evidence:bodleian-catalog",
          "evidence:bodleian-access",
          "evidence:astr-xml"
        ],
        "id": "question:astr-facsimiles",
        "impact": "medium",
        "last_checked": "2026-07-11",
        "next_steps": [
          "Search each repository catalog by exact shelfmark and contact the holding library about digitization or reproduction."
        ],
        "question": "Are complete public digital facsimiles now available for Dd.3.53, E.2, Digby 72, or Bodley 619?",
        "status": "no_public_source_found"
      },
      {
        "evidence_ids": [
          "evidence:astr-xml",
          "evidence:umich-astr"
        ],
        "id": "question:astr-terms",
        "impact": "high",
        "last_checked": "2026-07-11",
        "next_steps": [
          "Obtain a written interpretation from U-M before redistributing the XML or a close derivative commercially.",
          "Keep copyright status and provider-contract status separate."
        ],
        "question": "Does U-M's current NoC-US statement supersede the 1997 XML restriction against redistribution by commercial or not-for-profit content providers?",
        "status": "unresolved"
      }
    ],
    "primarySubjectId": "artifact:general-corpus:ChaucerAstr",
    "recordStatus": "partial",
    "relationClassification": null,
    "relations": [
      {
        "assertion": {
          "confidence": "high",
          "evidence_ids": [
            "evidence:astr-xml",
            "evidence:umich-astr"
          ],
          "status": "supported"
        },
        "id": "relation:astr-repo-from-umich",
        "objectId": "encoding:umich-cme:ChaucerAstr",
        "objectLabel": "University of Michigan CME item ChaucerAstr",
        "scope": {
          "object": {
            "description": "U-M item ChaucerAstr",
            "kind": "whole"
          },
          "subject": {
            "description": "Repository XML",
            "kind": "whole"
          }
        },
        "subjectId": "artifact:general-corpus:ChaucerAstr",
        "subjectLabel": "General Corpus source XML for ChaucerAstr",
        "type": "copied_from"
      },
      {
        "assertion": {
          "confidence": "high",
          "evidence_ids": [
            "evidence:astr-xml",
            "evidence:skeat-scan"
          ],
          "status": "confirmed"
        },
        "id": "relation:astr-umich-from-skeat",
        "objectId": "edition:skeat:astrolabe-1872",
        "objectLabel": "Skeat 1872 edition of A Treatise on the Astrolabe",
        "scope": {
          "notes": "The XML says front matter and textual notes were excluded while source organization and square brackets were retained.",
          "object": {
            "description": "Skeat's medieval text",
            "kind": "selected_passages",
            "locators": [
              "Prologue; Part I; Part II"
            ]
          },
          "subject": {
            "description": "Electronic edition",
            "kind": "whole"
          }
        },
        "subjectId": "encoding:umich-cme:ChaucerAstr",
        "subjectLabel": "University of Michigan CME item ChaucerAstr",
        "type": "encoded_from"
      },
      {
        "assertion": {
          "confidence": "high",
          "evidence_ids": [
            "evidence:astr-xml",
            "evidence:skeat-introduction"
          ],
          "status": "confirmed"
        },
        "id": "relation:skeat-transcribes-dd353",
        "objectId": "witness:cul:Dd3-53",
        "objectLabel": "Cambridge University Library MS Dd.3.53",
        "scope": {
          "object": {
            "description": "Corresponding text in Dd.3.53",
            "kind": "selected_passages"
          },
          "subject": {
            "description": "Core treatise",
            "kind": "selected_passages",
            "locators": [
              "Prologue",
              "Part I.1–23",
              "Part II.1–40"
            ]
          }
        },
        "subjectId": "edition:skeat:astrolabe-1872",
        "subjectLabel": "Skeat 1872 edition of A Treatise on the Astrolabe",
        "type": "transcribes"
      },
      {
        "assertion": {
          "confidence": "high",
          "evidence_ids": [
            "evidence:astr-xml",
            "evidence:skeat-scan"
          ],
          "status": "confirmed"
        },
        "id": "relation:skeat-transcribes-e2",
        "objectId": "witness:stjohn:E2",
        "objectLabel": "St John's College Cambridge MS E.2",
        "scope": {
          "object": {
            "description": "Corresponding text in E.2",
            "kind": "selected_passages"
          },
          "subject": {
            "description": "Supplementary conclusions",
            "kind": "selected_passages",
            "locators": [
              "Part II.41–43",
              "Part II.46–50"
            ]
          }
        },
        "subjectId": "edition:skeat:astrolabe-1872",
        "subjectLabel": "Skeat 1872 edition of A Treatise on the Astrolabe",
        "type": "transcribes"
      },
      {
        "assertion": {
          "confidence": "high",
          "evidence_ids": [
            "evidence:astr-xml",
            "evidence:skeat-scan"
          ],
          "status": "confirmed"
        },
        "id": "relation:skeat-transcribes-digby72",
        "objectId": "witness:bodleian:Digby72",
        "objectLabel": "Bodleian Library MS Digby 72",
        "scope": {
          "object": {
            "description": "Corresponding text in Digby 72",
            "kind": "selected_passages"
          },
          "subject": {
            "description": "Supplementary conclusions",
            "kind": "selected_passages",
            "locators": [
              "Part II.44–45"
            ]
          }
        },
        "subjectId": "edition:skeat:astrolabe-1872",
        "subjectLabel": "Skeat 1872 edition of A Treatise on the Astrolabe",
        "type": "transcribes"
      },
      {
        "assertion": {
          "confidence": "high",
          "evidence_ids": [
            "evidence:astr-xml",
            "evidence:skeat-scan"
          ],
          "status": "confirmed"
        },
        "id": "relation:skeat-transcribes-bodley619",
        "objectId": "witness:bodleian:Bodley619",
        "objectLabel": "Bodleian Library MS Bodley 619",
        "scope": {
          "object": {
            "description": "Corresponding text in Bodley 619",
            "kind": "selected_passages"
          },
          "subject": {
            "description": "Supplementary conclusion II.51",
            "kind": "part",
            "locators": [
              "Part II.51"
            ]
          }
        },
        "subjectId": "edition:skeat:astrolabe-1872",
        "subjectLabel": "Skeat 1872 edition of A Treatise on the Astrolabe",
        "type": "transcribes"
      }
    ],
    "reviewNotes": [
      "The four manuscript witnesses have explicitly different section scopes; no one manuscript is the source of the whole electronic text.",
      "Authorship of supplementary conclusions II.41–51 is separated from the secure attribution of the Prologue, Part I, and Part II.1–40.",
      "The local 1997 availability notice and U-M's current No Copyright–United States statement are recorded independently."
    ],
    "sourceLinks": [
      {
        "accessMethod": "Read checked-out CME submodule path",
        "alternateUrls": [],
        "contact": null,
        "cost": "not_applicable",
        "entityId": "artifact:general-corpus:ChaucerAstr",
        "entityLabel": "General Corpus source XML for ChaucerAstr",
        "entityType": "repository_artifact",
        "format": "XML",
        "id": "access:astr-repo",
        "lastChecked": "2026-07-11",
        "localCopies": [],
        "notes": [],
        "provider": "Kyvero Press",
        "resourceKind": "repository_file",
        "rights": [],
        "status": "local_only",
        "url": null
      },
      {
        "accessMethod": "U-M item and full text",
        "alternateUrls": [],
        "contact": null,
        "cost": "free",
        "entityId": "encoding:umich-cme:ChaucerAstr",
        "entityLabel": "University of Michigan CME item ChaucerAstr",
        "entityType": "digital_encoding",
        "format": "HTML digital text",
        "id": "access:astr-umich",
        "lastChecked": "2026-07-11",
        "localCopies": [],
        "notes": [],
        "provider": "University of Michigan Library",
        "resourceKind": "digital_text",
        "rights": [],
        "status": "publicly_available",
        "url": "https://name.umdl.umich.edu/ChaucerAstr"
      },
      {
        "accessMethod": "Public scan with exact direct PDF download",
        "alternateUrls": [
          "https://archive.org/details/onastrol00chautreatiserich",
          "https://archive.org/download/onastrol00chautreatiserich/onastrol00chautreatiserich.pdf"
        ],
        "contact": null,
        "cost": "free",
        "entityId": "edition:skeat:astrolabe-1872",
        "entityLabel": "Skeat 1872 edition of A Treatise on the Astrolabe",
        "entityType": "scholarly_edition",
        "format": "Google Books/Internet Archive complete page-image PDF",
        "id": "access:skeat-scan",
        "lastChecked": "2026-07-11",
        "localCopies": [
          {
            "available": false,
            "bundleSourceKind": null,
            "bytes": 15710387,
            "coverage": "complete",
            "downloadedOn": "2026-07-11",
            "label": "Skeat Astrolabe 1872 complete scan",
            "mediaType": "application/pdf",
            "notes": [
              "Complete 220-page provider PDF, retaining scan matter, preface, edited Middle English text, critical and additional notes, Latin comparison text, glossary, publication lists, and library matter."
            ],
            "path": "source-cache/ChaucerAstr/skeat-astrolabe-1872-complete.pdf",
            "retrievalMethod": "direct_download",
            "sha256": "4d728c89b68fb7d2f253e6ccd43fedf02c0803b33afb0ea0ed01caa31daea2bf",
            "sizeLabel": "15.0 MiB",
            "sourceFileCount": null,
            "sourceUrl": "https://archive.org/download/onastrol00chautreatiserich/onastrol00chautreatiserich.pdf",
            "workPortion": {
              "endUrl": "https://archive.org/download/onastrol00chautreatiserich/onastrol00chautreatiserich.pdf#page=148",
              "label": "Skeat's edited Middle English Treatise on the Astrolabe",
              "locators": [
                "printed pp. 1-60",
                "PDF pages 89-148",
                "Prologue; Part I; Part II.1-46 with supplied sections"
              ],
              "notes": [
                "Direct page inspection places the opening Prologue at PDF page 89 and the end of the edited Middle English text at PDF page 148; critical notes begin on PDF page 149."
              ],
              "startUrl": "https://archive.org/download/onastrol00chautreatiserich/onastrol00chautreatiserich.pdf#page=89"
            }
          }
        ],
        "notes": [
          "The ignored local cache is a complete scan of the printed edition, not a manuscript facsimile and not a separate grant of scan-image reuse rights."
        ],
        "provider": null,
        "resourceKind": "page_images",
        "rights": [],
        "status": "publicly_available",
        "url": "https://books.google.com/books?id=rIINAAAAQAAJ"
      },
      {
        "accessMethod": "Contact Cambridge University Library Manuscripts Department using shelfmark Dd.3.53",
        "alternateUrls": [],
        "contact": null,
        "cost": "unknown",
        "entityId": "witness:cul:Dd3-53",
        "entityLabel": "Cambridge University Library MS Dd.3.53",
        "entityType": "manuscript_witness",
        "format": null,
        "id": "access:dd353-enquiry",
        "lastChecked": "2026-07-11",
        "localCopies": [],
        "notes": [
          "No complete public facsimile was verified in this research pass."
        ],
        "provider": "Cambridge University Library",
        "resourceKind": "repository_enquiry",
        "rights": [],
        "status": "requestable",
        "url": "https://www.lib.cam.ac.uk/collections/departments/manuscripts-university-archives"
      },
      {
        "accessMethod": "Email St John's Special Collections and request an appointment using shelfmark E.2",
        "alternateUrls": [
          "https://www.joh.cam.ac.uk/research/library/old-library"
        ],
        "contact": null,
        "cost": "unknown",
        "entityId": "witness:stjohn:E2",
        "entityLabel": "St John's College Cambridge MS E.2",
        "entityType": "manuscript_witness",
        "format": null,
        "id": "access:e2-enquiry",
        "lastChecked": "2026-07-11",
        "localCopies": [],
        "notes": [
          "No complete public facsimile or item-specific image terms were verified in this research pass."
        ],
        "provider": "St John's College, Cambridge",
        "resourceKind": "repository_enquiry",
        "rights": [],
        "status": "requestable",
        "url": "https://www.joh.cam.ac.uk/contact-us"
      },
      {
        "accessMethod": "Request or enquire through Bodleian Special Collections using shelfmark MS. Digby 72",
        "alternateUrls": [
          "https://www.bodleian.ox.ac.uk/collections-and-resources/special-collections/ordering/requests",
          "https://archives.bodleian.ox.ac.uk/repositories/2/resources/7554"
        ],
        "contact": null,
        "cost": "unknown",
        "entityId": "witness:bodleian:Digby72",
        "entityLabel": "Bodleian Library MS Digby 72",
        "entityType": "manuscript_witness",
        "format": null,
        "id": "access:digby72-enquiry",
        "lastChecked": "2026-07-11",
        "localCopies": [],
        "notes": [
          "No complete public facsimile was verified in this research pass."
        ],
        "provider": "Bodleian Libraries, University of Oxford",
        "resourceKind": "repository_enquiry",
        "rights": [],
        "status": "requestable",
        "url": "https://www.bodleian.ox.ac.uk/collections-and-resources/special-collections/using"
      },
      {
        "accessMethod": "Request or enquire through Bodleian Special Collections using shelfmark MS. Bodley 619",
        "alternateUrls": [
          "https://www.bodleian.ox.ac.uk/collections-and-resources/special-collections/ordering/requests"
        ],
        "contact": null,
        "cost": "unknown",
        "entityId": "witness:bodleian:Bodley619",
        "entityLabel": "Bodleian Library MS Bodley 619",
        "entityType": "manuscript_witness",
        "format": null,
        "id": "access:bodley619-enquiry",
        "lastChecked": "2026-07-11",
        "localCopies": [],
        "notes": [
          "No complete public facsimile was verified in this research pass."
        ],
        "provider": "Bodleian Libraries, University of Oxford",
        "resourceKind": "repository_enquiry",
        "rights": [],
        "status": "requestable",
        "url": "https://www.bodleian.ox.ac.uk/collections-and-resources/special-collections/using"
      }
    ],
    "summary": "The repository XML is a local copy or version of U-M CME item ChaucerAstr, keyed by OCR from Walter W. Skeat's 1872 EETS edition of Chaucer's Treatise on the Astrolabe. Skeat's text uses Cambridge University Library MS Dd.3.53 for the Prologue, Part I.1–23, and Part II.1–40, then appends conclusions from St John's College Cambridge MS E.2, Bodleian MS Digby 72, and Bodleian MS Bodley 619. Modern scholarship generally treats the conclusions after II.40 as supplementary and probably non-Chaucerian, while leaving the precise authentic boundary open."
  },
  "lineageManifestPath": "catalog/manifests/lineage/ChaucerAstr.json",
  "metadata": {
    "catalogSummary": {
      "author": "Geoffrey Chaucer; supplementary conclusions of uncertain authorship",
      "date": "Core dated 1391; additions dated 1393 or later",
      "editor": "Walter W. Skeat",
      "form": "prose",
      "genres": [
        "Scientific treatise",
        "Technical manual",
        "Instructional prose"
      ],
      "language_codes": [
        "enm",
        "lat"
      ],
      "region": "England; exact place of composition not securely established",
      "tags": [
        "astrolabe",
        "astronomy",
        "astrology",
        "chaucer",
        "instrumentation",
        "instructional",
        "mathematics",
        "middle-english",
        "prose",
        "science",
        "timekeeping",
        "translation-and-adaptation"
      ],
      "title": "A Treatise on the Astrolabe"
    },
    "catalogingSubject": {
      "id": "work:ChaucerAstr",
      "label": "A Treatise on the Astrolabe",
      "scope_note": "The Middle English prose treatise addressed to Lowys, comprising a Chaucerian core (Prologue, Part I.1–23, and Part II.1–40) plus eleven supplementary conclusions (Part II.41–51) of uncertain authorship as assembled in Skeat's 1872 edition and U-M CME item ChaucerAstr. Skeat's modern front matter and textual notes are excluded from the cataloged medieval composite.",
      "unit_type": "composite"
    },
    "contentParts": [
      {
        "evidence_ids": [
          "evidence:astr-xml"
        ],
        "id": "part:prologue",
        "item_count": 1,
        "label": "Prologue",
        "locators": [
          {
            "lineage_entity_id": "edition:skeat:astrolabe-1872",
            "scheme": "part",
            "value": "Prologue"
          }
        ],
        "metrics": {
          "prose_only_items": 1,
          "verse_only_items": 0
        },
        "parent_id": null,
        "sequence": 1,
        "summary": "Chaucer addresses ten-year-old Lowys, dates the work to 1391, explains his vernacular purpose, and outlines a planned five-part manual.",
        "textual_form": "prose",
        "type": "prologue"
      },
      {
        "evidence_ids": [
          "evidence:astr-xml",
          "evidence:astr-structure"
        ],
        "id": "part:part-i",
        "item_count": 23,
        "label": "Part I: Description of the Astrolabe",
        "locators": [
          {
            "lineage_entity_id": "edition:skeat:astrolabe-1872",
            "scheme": "part-and-sections",
            "value": "Part I.1–23"
          }
        ],
        "metrics": {
          "prose_only_items": 23,
          "verse_only_items": 0
        },
        "parent_id": null,
        "sequence": 2,
        "summary": "Twenty-three sections identify and explain the ring, mother, plates, rete, rule, alidade, scales, circles, stars, and other components of the instrument.",
        "textual_form": "prose",
        "type": "section"
      },
      {
        "evidence_ids": [
          "evidence:astr-xml",
          "evidence:astr-structure"
        ],
        "id": "part:part-ii-core",
        "item_count": 40,
        "label": "Part II.1–40: Core Conclusions",
        "locators": [
          {
            "lineage_entity_id": "edition:skeat:astrolabe-1872",
            "scheme": "part-and-sections",
            "value": "Part II.1–40"
          }
        ],
        "metrics": {
          "prose_only_items": 40,
          "verse_only_items": 0
        },
        "parent_id": null,
        "sequence": 3,
        "summary": "Forty procedures use the instrument to determine celestial positions, time, latitude, ascensions, planetary conditions, and related quantities.",
        "textual_form": "prose",
        "type": "section"
      },
      {
        "evidence_ids": [
          "evidence:astr-xml",
          "evidence:supplement-authorship",
          "evidence:astr-structure"
        ],
        "id": "part:part-ii-supplement",
        "item_count": 11,
        "label": "Supplementary Conclusions II.41–51",
        "locators": [
          {
            "lineage_entity_id": "edition:skeat:astrolabe-1872",
            "scheme": "part-and-sections",
            "value": "Part II.41–51"
          }
        ],
        "metrics": {
          "prose_only_items": 11,
          "verse_only_items": 0
        },
        "notes": [
          "The XML node numbering is normalized to II.41–51, while several displayed headings reproduce alternate numbering such as 41a, 41b, 42a, and 42b."
        ],
        "parent_id": null,
        "sequence": 4,
        "summary": "Eleven additional procedures on shadows, heights, mean motion, and related calculations, printed from St John's E.2, Digby 72, and Bodley 619 and generally regarded as later supplements.",
        "textual_form": "prose",
        "type": "appendix"
      }
    ],
    "contentStructureStatus": "complete",
    "dateStatements": [
      {
        "assertion": {
          "confidence": "high",
          "evidence_ids": [
            "evidence:astr-xml",
            "evidence:chaucer-chronology"
          ],
          "status": "confirmed"
        },
        "display": "1391",
        "id": "date:core-composition",
        "normalized": {
          "not_after": 1391,
          "not_before": 1391
        },
        "notes": [
          "The prologue explicitly identifies the year and Lowys's age; the plan described there was not fully completed in the surviving core."
        ],
        "scope": {
          "kind": "part",
          "part_ids": [
            "part:prologue",
            "part:part-i",
            "part:part-ii-core"
          ]
        },
        "type": "composition"
      },
      {
        "assertion": {
          "confidence": "medium",
          "evidence_ids": [
            "evidence:chaucer-chronology",
            "evidence:supplement-authorship"
          ],
          "status": "supported"
        },
        "display": "1393 or later additions in the textual tradition",
        "id": "date:supplementary-additions",
        "normalized": {
          "not_before": 1393
        },
        "notes": [
          "This dates additions associated with the textual tradition; it does not assign their authorship to Chaucer."
        ],
        "scope": {
          "kind": "part",
          "part_ids": [
            "part:part-ii-supplement"
          ]
        },
        "type": "revision"
      }
    ],
    "extent": {
      "description": "Seventy-five cataloged content units: one unnumbered prologue plus 74 numbered instructional sections. Part I has 23 sections and Part II has 51, of which II.1–40 form the core and II.41–51 are supplementary. The XML's node sequence numbers all 51 Part II divisions even where Skeat's displayed supplement headings repeat 41–43-style numbers.",
      "evidence_ids": [
        "evidence:astr-structure"
      ],
      "mixed_items": 0,
      "numbered_items": 75,
      "prose_only_items": 75,
      "sections": 3,
      "verse_groups": 0,
      "verse_lines": 0,
      "verse_only_items": 0
    },
    "formStatements": [
      {
        "assertion": {
          "confidence": "high",
          "evidence_ids": [
            "evidence:astr-xml",
            "evidence:astrolabe-scholarship"
          ],
          "status": "confirmed"
        },
        "description": "A prose instructional treatise organized as a prologue, a description of the instrument, and numbered operational conclusions.",
        "id": "form:whole",
        "scope": {
          "kind": "whole"
        },
        "value": "prose"
      }
    ],
    "genres": [
      {
        "assertion": {
          "confidence": "high",
          "evidence_ids": [
            "evidence:astrolabe-scholarship"
          ],
          "status": "confirmed"
        },
        "id": "genre:scientific-treatise",
        "label": "Scientific treatise",
        "primary": true,
        "scheme": "general-corpus",
        "scope": {
          "kind": "whole"
        },
        "term": "scientific-treatise"
      },
      {
        "assertion": {
          "confidence": "high",
          "evidence_ids": [
            "evidence:astrolabe-scholarship",
            "evidence:astr-xml"
          ],
          "status": "confirmed"
        },
        "id": "genre:technical-manual",
        "label": "Technical manual",
        "primary": true,
        "scheme": "general-corpus",
        "scope": {
          "kind": "whole"
        },
        "term": "technical-manual"
      },
      {
        "assertion": {
          "confidence": "high",
          "evidence_ids": [
            "evidence:astr-xml"
          ],
          "status": "confirmed"
        },
        "id": "genre:instructional-prose",
        "label": "Instructional prose",
        "scheme": "general-corpus",
        "scope": {
          "kind": "whole"
        },
        "term": "instructional-prose"
      }
    ],
    "languageStatements": [
      {
        "assertion": {
          "confidence": "high",
          "evidence_ids": [
            "evidence:astr-xml",
            "evidence:skeat-edition"
          ],
          "status": "confirmed"
        },
        "code": "enm",
        "id": "language:middle-english",
        "label": "Middle English",
        "scope": {
          "kind": "whole"
        },
        "script": "Latn",
        "usage": "primary"
      },
      {
        "assertion": {
          "confidence": "high",
          "evidence_ids": [
            "evidence:astr-xml",
            "evidence:skeat-edition"
          ],
          "status": "confirmed"
        },
        "code": "lat",
        "id": "language:latin",
        "label": "Latin",
        "scope": {
          "description": "Latin headings, terms, and phrases occur throughout the Middle English instructions",
          "kind": "whole"
        },
        "script": "Latn",
        "usage": "embedded"
      }
    ],
    "lastReviewed": "2026-07-11",
    "manifestId": "metadata:ChaucerAstr",
    "notes": [
      "Oxford is recorded as an operational associated place because the treatise uses its latitude; it is not asserted as the place of composition.",
      "The XML's sequential nodes II.41–51 and Skeat's displayed supplement numbering are both preserved conceptually; users should cite the displayed heading when precision matters.",
      "A four-witness edition with scoped supplements must not inherit a single manuscript's dialect or physical description at work level."
    ],
    "openQuestions": [
      {
        "evidence_ids": [
          "evidence:supplement-authorship",
          "evidence:astr-xml",
          "evidence:lineage-astr"
        ],
        "id": "question:supplement-authorship",
        "impact": "high",
        "last_checked": "2026-07-11",
        "next_steps": [
          "Consult the Variorum textual introduction and current manuscript scholarship; continue to display the supplementary stratum separately."
        ],
        "question": "Which, if any, conclusions after Part II.40 are Chaucer's?",
        "status": "unresolved"
      },
      {
        "evidence_ids": [
          "evidence:astrolabe-scholarship"
        ],
        "id": "question:source-strata",
        "impact": "medium",
        "last_checked": "2026-07-11",
        "next_steps": [
          "Use Eagleton's source analysis and the Variorum commentary to map source relationships section by section rather than naming one universal exemplar."
        ],
        "question": "Which particular Latin exemplars and intermediary compilations underlie each part of Chaucer's core treatise?",
        "status": "unresolved"
      },
      {
        "evidence_ids": [
          "evidence:astr-xml"
        ],
        "id": "question:lowys-identity",
        "impact": "low",
        "last_checked": "2026-07-11",
        "next_steps": [
          "Consult current Chaucer biography and documentary scholarship before adding an authority record or biographical claims."
        ],
        "question": "Can the addressee Lowys be independently identified beyond the text's description ‘my sone’ and age ten?",
        "status": "unresolved"
      },
      {
        "evidence_ids": [
          "evidence:astr-xml",
          "evidence:astr-umich",
          "evidence:lineage-astr"
        ],
        "id": "question:provider-terms",
        "impact": "high",
        "last_checked": "2026-07-11",
        "next_steps": [
          "Seek written clarification from U-M before redistributing the XML or a close derivative, especially through a for-profit service."
        ],
        "question": "Do U-M's current NoC-US statement and access interface supersede the redistribution restriction embedded in the 1997 XML?",
        "status": "unresolved"
      }
    ],
    "placeStatements": [
      {
        "assertion": {
          "confidence": "high",
          "evidence_ids": [
            "evidence:astr-umich",
            "evidence:astrolabe-scholarship"
          ],
          "status": "confirmed"
        },
        "id": "place-statement:england",
        "notes": [
          "This is not an assertion of an exact place of composition or a single scribal dialect."
        ],
        "placeLabel": "England",
        "place_id": "place:england",
        "scope": {
          "kind": "whole"
        },
        "type": "cultural_origin"
      },
      {
        "assertion": {
          "confidence": "high",
          "evidence_ids": [
            "evidence:astr-xml"
          ],
          "status": "confirmed"
        },
        "id": "place-statement:oxford-latitude",
        "notes": [
          "Operational association with Oxford does not prove that the treatise was composed there."
        ],
        "placeLabel": "Oxford",
        "place_id": "place:oxford",
        "scope": {
          "description": "Part II uses Oxford as a practical latitude and place reference",
          "kind": "part",
          "part_ids": [
            "part:part-ii-core"
          ]
        },
        "type": "associated_place"
      }
    ],
    "recordStatus": "partial",
    "responsibilities": [
      {
        "agentName": "Geoffrey Chaucer",
        "agent_id": "agent:geoffrey-chaucer",
        "assertion": {
          "confidence": "high",
          "evidence_ids": [
            "evidence:astr-umich",
            "evidence:astrolabe-scholarship",
            "evidence:supplement-authorship"
          ],
          "status": "confirmed"
        },
        "attribution_status": "known",
        "id": "responsibility:chaucer-author",
        "role": "author",
        "scope": {
          "description": "Securely Chaucerian core through Part II.40",
          "kind": "part",
          "part_ids": [
            "part:prologue",
            "part:part-i",
            "part:part-ii-core"
          ]
        }
      },
      {
        "agentName": "Geoffrey Chaucer",
        "agent_id": "agent:geoffrey-chaucer",
        "assertion": {
          "confidence": "high",
          "evidence_ids": [
            "evidence:astrolabe-scholarship"
          ],
          "status": "supported"
        },
        "attribution_status": "known",
        "id": "responsibility:chaucer-translator",
        "role": "translator",
        "scope": {
          "description": "Translation and reworking of Latin astrolabe traditions",
          "kind": "part",
          "part_ids": [
            "part:prologue",
            "part:part-i",
            "part:part-ii-core"
          ]
        }
      },
      {
        "agentName": "Geoffrey Chaucer",
        "agent_id": "agent:geoffrey-chaucer",
        "assertion": {
          "confidence": "high",
          "evidence_ids": [
            "evidence:astr-xml",
            "evidence:astrolabe-scholarship"
          ],
          "status": "supported"
        },
        "attribution_status": "known",
        "id": "responsibility:chaucer-adapter",
        "role": "adapter",
        "scope": {
          "description": "Vernacular adaptation organized for an individual learner and instrument",
          "kind": "part",
          "part_ids": [
            "part:prologue",
            "part:part-i",
            "part:part-ii-core"
          ]
        }
      },
      {
        "agentName": "Anonymous astrolabe supplementer or supplementers",
        "agent_id": "agent:anonymous-supplementer",
        "assertion": {
          "confidence": "medium",
          "evidence_ids": [
            "evidence:astr-xml",
            "evidence:supplement-authorship"
          ],
          "notes": "Most scholarship treats these conclusions as non-Chaucerian additions, but the precise boundary and number of contributors remain uncertain.",
          "status": "supported"
        },
        "attribution_status": "disputed",
        "id": "responsibility:supplement-attributed",
        "notes": [
          "Do not display the whole 51-conclusion Part II as unqualified Chaucerian authorship."
        ],
        "role": "attributed_author",
        "scope": {
          "description": "Supplementary conclusions II.41–51",
          "kind": "part",
          "part_ids": [
            "part:part-ii-supplement"
          ]
        }
      },
      {
        "agentName": "Walter W. Skeat",
        "agent_id": "agent:walter-skeat",
        "assertion": {
          "confidence": "high",
          "evidence_ids": [
            "evidence:astr-xml",
            "evidence:skeat-edition"
          ],
          "status": "confirmed"
        },
        "attribution_status": "known",
        "id": "responsibility:skeat-editor",
        "role": "editor",
        "scope": {
          "kind": "whole"
        }
      },
      {
        "agentName": "Walter W. Skeat",
        "agent_id": "agent:walter-skeat",
        "assertion": {
          "confidence": "high",
          "evidence_ids": [
            "evidence:astr-xml",
            "evidence:skeat-edition",
            "evidence:lineage-astr"
          ],
          "status": "confirmed"
        },
        "attribution_status": "known",
        "id": "responsibility:skeat-transcriber",
        "role": "transcriber",
        "scope": {
          "description": "Printed text assembled from four specified manuscript witnesses",
          "kind": "whole"
        }
      },
      {
        "agentName": "Walter W. Skeat",
        "agent_id": "agent:walter-skeat",
        "assertion": {
          "confidence": "high",
          "evidence_ids": [
            "evidence:astr-xml",
            "evidence:skeat-edition",
            "evidence:lineage-astr"
          ],
          "status": "confirmed"
        },
        "attribution_status": "known",
        "id": "responsibility:skeat-collator",
        "role": "collator",
        "scope": {
          "kind": "whole"
        }
      }
    ],
    "subjects": [
      {
        "assertion": {
          "confidence": "high",
          "evidence_ids": [
            "evidence:astr-xml",
            "evidence:astrolabe-scholarship"
          ],
          "status": "confirmed"
        },
        "id": "subject:astrolabe",
        "label": "Astrolabe construction and use",
        "primary": true,
        "scheme": "general-corpus",
        "scope": {
          "kind": "whole"
        },
        "term": "astrolabe"
      },
      {
        "assertion": {
          "confidence": "high",
          "evidence_ids": [
            "evidence:astr-xml"
          ],
          "status": "confirmed"
        },
        "id": "subject:astronomy",
        "label": "Practical astronomy",
        "primary": true,
        "scheme": "general-corpus",
        "scope": {
          "kind": "whole"
        },
        "term": "astronomy"
      },
      {
        "assertion": {
          "confidence": "high",
          "evidence_ids": [
            "evidence:astr-xml"
          ],
          "status": "confirmed"
        },
        "id": "subject:timekeeping",
        "label": "Timekeeping and calendrical calculation",
        "scheme": "general-corpus",
        "scope": {
          "kind": "part",
          "part_ids": [
            "part:part-ii-core"
          ]
        },
        "term": "timekeeping"
      },
      {
        "assertion": {
          "confidence": "high",
          "evidence_ids": [
            "evidence:astr-xml",
            "evidence:astrolabe-scholarship"
          ],
          "status": "confirmed"
        },
        "id": "subject:instrumentation",
        "label": "Scientific instruments and measurement",
        "scheme": "general-corpus",
        "scope": {
          "kind": "whole"
        },
        "term": "instrumentation"
      },
      {
        "assertion": {
          "confidence": "high",
          "evidence_ids": [
            "evidence:astr-xml"
          ],
          "status": "confirmed"
        },
        "id": "subject:astrology",
        "label": "Medieval astrology and planetary calculation",
        "notes": [
          "The text includes astrological terminology and procedures while explicitly distancing itself from some judicial practices."
        ],
        "scheme": "general-corpus",
        "scope": {
          "kind": "part",
          "part_ids": [
            "part:part-ii-core",
            "part:part-ii-supplement"
          ]
        },
        "term": "astrology"
      }
    ],
    "summaries": [
      {
        "evidence_ids": [
          "evidence:astr-xml",
          "evidence:astrolabe-scholarship",
          "evidence:supplement-authorship"
        ],
        "id": "summary:abstract",
        "language": "eng",
        "scope": {
          "kind": "whole"
        },
        "type": "abstract",
        "value": "A Middle English prose manual explaining the parts and operation of a planispheric astrolabe for the learner Lowys. The core describes the instrument and gives numbered procedures for finding solar and stellar positions, time, latitude, ascensions, planetary positions, and related astronomical quantities. Skeat's edition appends eleven conclusions from other manuscripts whose Chaucerian authorship is doubtful."
      },
      {
        "evidence_ids": [
          "evidence:astr-xml",
          "evidence:supplement-authorship",
          "evidence:lineage-astr"
        ],
        "id": "summary:scope",
        "language": "eng",
        "scope": {
          "kind": "whole"
        },
        "type": "scope_note",
        "value": "The record models the edition as a composite so users can distinguish the securely attributed core through Part II.40 from conclusions II.41–51 supplied from three other manuscripts. This is an authorship and textual-boundary distinction, not merely a change of physical witness."
      }
    ],
    "tags": [
      "astrolabe",
      "astronomy",
      "astrology",
      "chaucer",
      "instrumentation",
      "instructional",
      "mathematics",
      "middle-english",
      "prose",
      "science",
      "timekeeping",
      "translation-and-adaptation"
    ],
    "titles": [
      {
        "assertion": {
          "confidence": "high",
          "evidence_ids": [
            "evidence:astr-umich",
            "evidence:skeat-edition"
          ],
          "status": "confirmed"
        },
        "id": "title:preferred",
        "language": "eng",
        "scope": {
          "kind": "whole"
        },
        "script": "Latn",
        "type": "preferred",
        "value": "A Treatise on the Astrolabe"
      },
      {
        "assertion": {
          "confidence": "high",
          "evidence_ids": [
            "evidence:astr-xml",
            "evidence:skeat-edition"
          ],
          "status": "confirmed"
        },
        "id": "title:alternate-address",
        "language": "eng",
        "scope": {
          "kind": "whole"
        },
        "script": "Latn",
        "type": "alternate",
        "value": "A Treatise on the Astrolabe Addressed to His Son Lowys"
      },
      {
        "assertion": {
          "confidence": "high",
          "evidence_ids": [
            "evidence:astr-xml"
          ],
          "status": "confirmed"
        },
        "id": "title:incipit",
        "language": "enm",
        "scope": {
          "kind": "part",
          "part_ids": [
            "part:prologue"
          ]
        },
        "script": "Latn",
        "type": "incipit",
        "value": "Lyte Lowys my sone"
      }
    ]
  },
  "metadataManifestPath": "catalog/manifests/work-metadata/ChaucerAstr.json",
  "schemaVersion": "1.0.0",
  "work": {
    "author": "Geoffrey Chaucer; supplementary conclusions of uncertain authorship",
    "dateDisplay": "Core dated 1391; additions dated 1393 or later",
    "detailPath": "catalog/works/ChaucerAstr.json",
    "displayTitle": "A Treatise on the Astrolabe",
    "editor": "Walter W. Skeat",
    "form": "prose",
    "genres": [
      {
        "label": "Scientific treatise",
        "term": "scientific-treatise"
      },
      {
        "label": "Technical manual",
        "term": "technical-manual"
      },
      {
        "label": "Instructional prose",
        "term": "instructional-prose"
      }
    ],
    "languages": [
      {
        "code": "enm",
        "label": "Middle English"
      },
      {
        "code": "lat",
        "label": "Latin"
      }
    ],
    "lastReviewed": "2026-07-11",
    "lineageStatus": "available",
    "metadataRecordStatus": "partial",
    "metadataStatus": "cataloged",
    "preferredTitle": "A Treatise on the Astrolabe",
    "publication": {
      "bytes": 228408,
      "embeddedAuthor": "Chaucer, Geoffrey, d. 1400",
      "embeddedTitle": "Treatise on The Astrolabe: addressed to his son Lowys / by Geoffrey Chaucer; edited from the earliest MSS. by Walter W. Skeat",
      "externalUrl": "https://github.com/Kyvero-Press/General-Corpus/releases/download/publication-set-2026-07-11/ChaucerAstr.pdf",
      "filename": "ChaucerAstr.pdf",
      "pageSize": "360 x 576 pts",
      "pages": 88,
      "path": null,
      "sha256": "0df084800f2f71060f3258e526249a8720e03b9b4d113cd1f8e424138b58b1d1",
      "sizeLabel": "223 KiB",
      "status": "available"
    },
    "publicationYear": null,
    "regionDisplay": "England; exact place of composition not securely established",
    "regions": [
      {
        "label": "England",
        "relation": "cultural_origin"
      },
      {
        "label": "Oxford",
        "relation": "associated_place"
      }
    ],
    "sourcePeriods": [],
    "subjects": [
      {
        "label": "Astrolabe construction and use",
        "term": "astrolabe"
      },
      {
        "label": "Practical astronomy",
        "term": "astronomy"
      },
      {
        "label": "Timekeeping and calendrical calculation",
        "term": "timekeeping"
      },
      {
        "label": "Scientific instruments and measurement",
        "term": "instrumentation"
      },
      {
        "label": "Medieval astrology and planetary calculation",
        "term": "astrology"
      }
    ],
    "summary": "A Middle English prose manual explaining the parts and operation of a planispheric astrolabe for the learner Lowys. The core describes the instrument and gives numbered procedures for finding solar and stellar positions, time, latitude, ascensions, planetary positions, and related astronomical quantities. Skeat's edition appends eleven conclusions from other manuscripts whose Chaucerian authorship is doubtful.",
    "tags": [
      "astrolabe",
      "astronomy",
      "astrology",
      "chaucer",
      "instrumentation",
      "instructional",
      "mathematics",
      "middle-english",
      "prose",
      "science",
      "timekeeping",
      "translation-and-adaptation"
    ],
    "translatedTitle": null,
    "workId": "ChaucerAstr"
  }
}
